odoo/addons/base_maintenance_group/README.rst
odoo/addons/base_maintenance_group/__init__.py
odoo/addons/base_maintenance_group/__manifest__.py
odoo/addons/base_maintenance_group/menuitems.xml
odoo/addons/base_maintenance_group/data/maintenance_data.xml
odoo/addons/base_maintenance_group/i18n/base_maintenance_group.pot
odoo/addons/base_maintenance_group/i18n/it.po
odoo/addons/base_maintenance_group/i18n/pt_BR.po
odoo/addons/base_maintenance_group/readme/CONTRIBUTORS.rst
odoo/addons/base_maintenance_group/readme/DESCRIPTION.rst
odoo/addons/base_maintenance_group/readme/USAGE.rst
odoo/addons/base_maintenance_group/security/maintenance_security.xml
odoo/addons/base_maintenance_group/static/description/icon.png
odoo/addons/base_maintenance_group/static/description/index.html
odoo14_addon_base_maintenance_group-14.0.1.0.1.dist-info/METADATA
odoo14_addon_base_maintenance_group-14.0.1.0.1.dist-info/WHEEL
odoo14_addon_base_maintenance_group-14.0.1.0.1.dist-info/top_level.txt
odoo14_addon_base_maintenance_group-14.0.1.0.1.dist-info/RECORD
